README.md
license.txt
pyproject.toml
setup.cfg
setup.py
skkklearning/__init__.py
skkklearning/sklearns.py
skkklearning.egg-info/PKG-INFO
skkklearning.egg-info/SOURCES.txt
skkklearning.egg-info/dependency_links.txt
skkklearning.egg-info/top_level.txt